MANIFEST.in
README.rst
bootstrap.py
buildout.cfg
fise-instance.in
setup.py
src/fise/__init__.py
src/fise.client.egg-info/PKG-INFO
src/fise.client.egg-info/SOURCES.txt
src/fise.client.egg-info/dependency_links.txt
src/fise.client.egg-info/namespace_packages.txt
src/fise.client.egg-info/requires.txt
src/fise.client.egg-info/top_level.txt
src/fise.client.egg-info/zip-safe
src/fise/client/__init__.py
src/fise/client/base.py
src/fise/client/engines.py
src/fise/client/engines.txt
src/fise/client/store.py
src/fise/client/store.txt
src/fise/client/tests.py