Metadata-Version: 1.0
Name: fise.client
Version: 1.1
Summary: Apache Stanbol FISE: RESTful Python Client.
Home-page: UNKNOWN
Author: Jens Klein
Author-email: jens@bluedynamics.com
License: Python Software Foundation License
Platform: UNKNOWN
Classifier: Development Status :: 5 - Production/Stable
Classifier: License :: OSI Approved :: Python Software Foundation License
Classifier: Operating System :: OS Independent
Classifier: Programming Language :: Python
Classifier: Topic :: Software Development
